<net.rptools.maptool.model.MacroButtonProperties>
  <macroUUID>0db3fe1c-8b5a-4695-a7e5-d7ce8a0f5846</macroUUID>
  <saveLocation>Token</saveLocation>
  <index>16</index>
  <colorKey/>
  <hotKey>None</hotKey>
  <label>dndbt_Zairali</label>
  <group>Toon</group>
  <sortby/>
  <autoExecute>true</autoExecute>
  <includeLabel>false</includeLabel>
  <applyToTokens>false</applyToTokens>
  <fontColorKey>black</fontColorKey>
  <fontSize>1.00em</fontSize>
  <minWidth/>
  <maxWidth/>
  <allowPlayerEdits>true</allowPlayerEdits>
  <toolTip/>
  <displayHotKey>true</displayHotKey>
  <commonMacro>false</commonMacro>
  <compareGroup>true</compareGroup>
  <compareSortPrefix>true</compareSortPrefix>
  <compareCommand>true</compareCommand>
  <compareIncludeLabel>true</compareIncludeLabel>
  <compareAutoExecute>true</compareAutoExecute>
  <compareApplyToSelectedTokens>true</compareApplyToSelectedTokens>
</net.rptools.maptool.model.MacroButtonProperties>
