<net.rptools.maptool.model.MacroButtonProperties>
  <macroUUID>026f406a-1083-45fe-9133-b96f27bb62b4</macroUUID>
  <saveLocation>Token</saveLocation>
  <index>101</index>
  <colorKey/>
  <hotKey>None</hotKey>
  <label>dndbt_Yaichi</label>
  <group>Toon</group>
  <sortby/>
  <autoExecute>true</autoExecute>
  <includeLabel>false</includeLabel>
  <applyToTokens>false</applyToTokens>
  <fontColorKey>black</fontColorKey>
  <fontSize>1.00em</fontSize>
  <minWidth/>
  <maxWidth/>
  <allowPlayerEdits>true</allowPlayerEdits>
  <toolTip>27752286</toolTip>
  <displayHotKey>true</displayHotKey>
  <commonMacro>false</commonMacro>
  <compareGroup>true</compareGroup>
  <compareSortPrefix>true</compareSortPrefix>
  <compareCommand>true</compareCommand>
  <compareIncludeLabel>true</compareIncludeLabel>
  <compareAutoExecute>true</compareAutoExecute>
  <compareApplyToSelectedTokens>true</compareApplyToSelectedTokens>
</net.rptools.maptool.model.MacroButtonProperties>
