<net.rptools.maptool.model.MacroButtonProperties>
  <macroUUID>7a26362e-8d2f-47d9-bbf2-8a8ae81b4dee</macroUUID>
  <saveLocation>Token</saveLocation>
  <index>49</index>
  <colorKey>default</colorKey>
  <hotKey>None</hotKey>
  <label>dndbt_CreateDataMacro</label>
  <group>Meta Test</group>
  <sortby/>
  <autoExecute>true</autoExecute>
  <includeLabel>false</includeLabel>
  <applyToTokens>false</applyToTokens>
  <fontColorKey>black</fontColorKey>
  <fontSize>1.00em</fontSize>
  <minWidth/>
  <maxWidth/>
  <allowPlayerEdits>false</allowPlayerEdits>
  <toolTip/>
  <displayHotKey>true</displayHotKey>
  <commonMacro>false</commonMacro>
  <compareGroup>true</compareGroup>
  <compareSortPrefix>true</compareSortPrefix>
  <compareCommand>true</compareCommand>
  <compareIncludeLabel>true</compareIncludeLabel>
  <compareAutoExecute>true</compareAutoExecute>
  <compareApplyToSelectedTokens>true</compareApplyToSelectedTokens>
</net.rptools.maptool.model.MacroButtonProperties>
