<net.rptools.maptool.model.MacroButtonProperties>
  <macroUUID>299b0690-6638-4bd6-9c61-25d65b5d50c3</macroUUID>
  <saveLocation>Token</saveLocation>
  <index>57</index>
  <colorKey>default</colorKey>
  <hotKey>None</hotKey>
  <label>dnd5e_RollExpression_addExpression</label>
  <group>RollExpression</group>
  <sortby/>
  <autoExecute>true</autoExecute>
  <includeLabel>false</includeLabel>
  <applyToTokens>false</applyToTokens>
  <fontColorKey>black</fontColorKey>
  <fontSize>1.00em</fontSize>
  <minWidth/>
  <maxWidth/>
  <allowPlayerEdits>false</allowPlayerEdits>
  <toolTip>Adds children expressions to the provided RollExpression. Child expression totals are added to the parent's total(s).

arg (0) = RollExpression
arg (1..n) = child RollExpressions

Returns RollExpression</toolTip>
  <displayHotKey>true</displayHotKey>
  <commonMacro>false</commonMacro>
  <compareGroup>true</compareGroup>
  <compareSortPrefix>true</compareSortPrefix>
  <compareCommand>true</compareCommand>
  <compareIncludeLabel>true</compareIncludeLabel>
  <compareAutoExecute>true</compareAutoExecute>
  <compareApplyToSelectedTokens>true</compareApplyToSelectedTokens>
</net.rptools.maptool.model.MacroButtonProperties>
